odoo/addons/ssi_letter_operating_unit/README.rst
odoo/addons/ssi_letter_operating_unit/__init__.py
odoo/addons/ssi_letter_operating_unit/__manifest__.py
odoo/addons/ssi_letter_operating_unit/models/__init__.py
odoo/addons/ssi_letter_operating_unit/models/incoming_letter.py
odoo/addons/ssi_letter_operating_unit/models/outgoing_letter.py
odoo/addons/ssi_letter_operating_unit/security/ir_rule/incoming_letter.xml
odoo/addons/ssi_letter_operating_unit/security/ir_rule/outgoing_letter.xml
odoo/addons/ssi_letter_operating_unit/security/res_group/incoming_letter.xml
odoo/addons/ssi_letter_operating_unit/security/res_group/outgoing_letter.xml
odoo/addons/ssi_letter_operating_unit/static/description/icon.png
odoo/addons/ssi_letter_operating_unit/views/incoming_letter_views.xml
odoo/addons/ssi_letter_operating_unit/views/outgoing_letter_views.xml
odoo14_addon_ssi_letter_operating_unit-14.0.1.0.0.dist-info/METADATA
odoo14_addon_ssi_letter_operating_unit-14.0.1.0.0.dist-info/WHEEL
odoo14_addon_ssi_letter_operating_unit-14.0.1.0.0.dist-info/top_level.txt
odoo14_addon_ssi_letter_operating_unit-14.0.1.0.0.dist-info/RECORD
